pyisv/__init__.py
pyisv/_version.py
pyisv/cnn.py
pyisv/eofs.py
pyisv/metrics.py
pyisv/plotting.py
pyisv/utils.py
pyisv-1.0.0.dist-info/LICENSE.md
pyisv-1.0.0.dist-info/METADATA
pyisv-1.0.0.dist-info/WHEEL
pyisv-1.0.0.dist-info/top_level.txt
pyisv-1.0.0.dist-info/RECORD
