Metadata-Version: 2.1
Name: pyisv
Version: 1.0.0
Summary: A Machine Learning Technique to Extract the Intra Seasonal Variability (ISV) from the Geophysical Data.
Home-page: https://github.com/ram-sridhar/pyisv
Author: Rama Sesha Sridhar Mantripragada
Author-email: ram.sridhar4@gmail.com
Classifier: Development Status :: 5 - Production/Stable
Classifier: License :: OSI Approved :: Apache Software License
Classifier: Programming Language :: Python :: 3
Classifier: Programming Language :: Python :: 3.10
License-File: LICENSE.md
